{
  "description": "Classify images.",
  "parameters": [
    {
      "name": "username",
      "required": false,
      "bindTime": true,
      "description": "The service username"
    },
    {
      "name": "password",
      "required": false,
      "bindTime": true,
      "description": "The service password"
    },
    {
      "name": "headers",
      "required": false,
      "bindTime": false,
      "description": "The request headers"
    },
    {
      "name": "headers.X-Watson-Learning-Opt-Out",
      "required": false,
      "bindTime": false,
      "description": "opt-out of data collection"
    },
    {
      "name": "url",
      "required": false,
      "bindTime": false,
      "description": "override default service base url"
    },
    {
      "name": "version_date",
      "required": true,
      "bindTime": false,
      "description": "Release date of the API version in YYYY-MM-DD format."
    },
    {
      "name": "images_file",
      "required": false,
      "bindTime": false,
      "description":
        "An image file (.jpg, .png) or .zip file with images. Include no more than 20 images and limit the .zip file to 5 MB. You can also include images with the `url` property in the **parameters** object."
    },
    {
      "name": "parameters",
      "required": false,
      "bindTime": false,
      "description":
        "Specifies input parameters. The parameter can include these inputs in a JSON object:  - url: A string with the image URL to analyze. You can also include images in the **images_file** parameter. - classifier_ids: An array of classifier IDs to classify the images against. - owners: An array with the values IBM, me, or both to specify which classifiers to run. - threshold: A floating point value that specifies the minimum score a class must have to be displayed in the response.  For example: {\"url\": \"...\", \"classifier_ids\": [\"...\",\"...\"], \"owners\": [\"IBM\", \"me\"], \"threshold\": 0.4}."
    },
    {
      "name": "accept_language",
      "required": false,
      "bindTime": false,
      "description":
        "Specifies the language of the output class names.  Can be `en` (English), `ar` (Arabic), `de` (German), `es` (Spanish), `it` (Italian), `ja` (Japanese), or `ko` (Korean).  Classes for which no translation is available are omitted.  The response might not be in the specified language under these conditions: - English is returned when the requested language is not supported. - Classes are not returned when there is no translation for them. - Custom classifiers returned with this method return tags in the language of the custom classifier."
    },
    {
      "name": "images_file_content_type",
      "required": false,
      "bindTime": false,
      "description": "The content type of images_file."
    }
  ],
  "sampleInput": {
    "username": "XXX",
    "password": "XXX",
    "version_date": "2016-10-19",
    "images_file": "{Base64 image data}"
  },
  "sampleOutput": {
    "custom_classes": 0,
    "images": [
      {
        "classifiers": [
          {
            "classes": [
              {
                "class": "banana",
                "score": 0.562,
                "type_hierarchy": "/fruit/banana"
              },
              {
                "class": "fruit",
                "score": 0.788
              },
              {
                "class": "diet (food)",
                "score": 0.528,
                "type_hierarchy": "/food/diet (food)"
              },
              {
                "class": "food",
                "score": 0.528
              },
              {
                "class": "honeydew",
                "score": 0.5,
                "type_hierarchy": "/fruit/melon/honeydew"
              },
              {
                "class": "melon",
                "score": 0.501
              },
              {
                "class": "olive color",
                "score": 0.973
              },
              {
                "class": "lemon yellow color",
                "score": 0.789
              }
            ],
            "classifier_id": "default",
            "name": "default"
          }
        ],
        "image": "fruitbowl.jpg"
      }
    ],
    "images_processed": 1
  }
}
